Workbook
Name Class_Band: Assumptions!$B$11
Name Cost_bps: Assumptions!$B$13
Name Eq_Target: Assumptions!$B$9
Name FI_Target: Assumptions!$B$10
Name Hold_Band: Assumptions!$B$12
Name Start_Value: Assumptions!$B$8
Name Tol: Assumptions!$B$14

Sheet Overview
A1: Market & Portfolio Report workbook: September 2026
A2: Independent educational research sample. Hypothetical portfolio. As of the September 30, 2026 close, CAD. Not investment advice.
A4: Portfolio return | B4: Benchmark (VBAL) return | C4: Difference (pp) | D4: Equity contribution (pp) | E4: Bond contribution (pp) | F4: Month-end decision
A5: =Holdings!I14 -> -0.0056766842 | B5: =Returns!F12 -> -0.0050275755 | C5: =Returns!F14 -> -0.064910867 | D5: =Contributions!E12 -> -0.029052147 | E5: =Contributions!E13 -> -0.53861627 | F5: =Holdings!C23 -> Maintain
A7: Rising rates hit bonds and credit, and the balanced mix lost 0.57% in September
A9: Rates and currency (Bank of Canada)
A10: Series | B10: Aug 31 | C10: Sep 30 | D10: Change | E10: Unit | F10: Latest observation
A11: USD/CAD (daily average) | B11: 1.3866 | C11: 1.4188 | D11: =C11/B11-1 -> 0.02322227 | E11: CAD per USD | F11: 46294
A12: Canada 2-year yield | B12: 3.01 | C12: 3.37 | D12: =(C12-B12)*100 -> 36 | E12: % | F12: 46294
A13: Canada 10-year yield | B13: 3.73 | C13: 3.99 | D13: =(C13-B13)*100 -> 26 | E13: % | F13: 46294
A14: Bank of Canada overnight target | B14: 2.25 | C14: 2.25 | D14: =(C14-B14)*100 -> 0 | E14: % | F14: 46295
A16: Chart order: portfolio solid navy, benchmark dashed slate; contribution bars in holdings order. Tables behind the charts are on Returns and Contributions.

Sheet Holdings
A1: Holdings and weights
A2: Independent educational research sample. Hypothetical portfolio. Blue = input weights; returns link to the Returns sheet.
A4: Ticker | B4: Fund | C4: Asset class | D4: Exposure | E4: Currency | F4: Target weight | G4: Start weight | H4: Start value (CAD) | I4: Total return | J4: End value (CAD) | K4: End weight | L4: Drift vs target | M4: Trade to target if reset | N4: Rationale
A5: XIC | B5: iShares Core S&P/TSX Capped Composite Index ETF | C5: Equity | D5: Canada | E5: CAD | F5: 0.2 | G5: 0.20346772 | H5: =Start_Value*G5 -> 20611.013 | I5: =Returns!F5 -> -0.026515966 | J5: =H5*(1+I5) -> 20064.492 | K5: =J5/J$14 -> 0.19920339 | L5: =(K5-F5)*100 -> -0.079661255 | M5: =(F5-K5)*100 -> 0.079661255 | N5: Domestic core: broad Canadian large, mid and small caps with no currency translation.
A6: XUU | B6: iShares Core S&P U.S. Total Market Index ETF | C6: Equity | D6: United States (USD, unhedged) | E6: CAD | F6: 0.25 | G6: 0.25058089 | H6: =Start_Value*G6 -> 25383.515 | I6: =Returns!F6 -> 0.019346216 | J6: =H6*(1+I6) -> 25874.59 | K6: =J6/J$14 -> 0.25688695 | L6: =(K6-F6)*100 -> 0.68869459 | M6: =(F6-K6)*100 -> -0.68869459 | N6: Largest equity market; unhedged so USD exposure diversifies Canadian-dollar risk.
A7: XEF | B7: iShares Core MSCI EAFE IMI Index ETF | C7: Equity | D7: Developed ex-North America (unhedged) | E7: CAD | F7: 0.1 | G7: 0.099669551 | H7: =Start_Value*G7 -> 10096.395 | I7: =Returns!F7 -> -0.0081153188 | J7: =H7*(1+I7) -> 10014.459 | K7: =J7/J$14 -> 0.099425106 | L7: =(K7-F7)*100 -> -0.057489447 | M7: =(F7-K7)*100 -> 0.057489447 | N7: Europe, Australasia and Far East exposure that is not tied to the North American cycle.
A8: XEC | B8: iShares Core MSCI Emerging Markets IMI Index ETF | C8: Equity | D8: Emerging markets (unhedged) | E8: CAD | F8: 0.05 | G8: 0.051443747 | H8: =Start_Value*G8 -> 5211.1842 | I8: =Returns!F8 -> 0.020715439 | J8: =H8*(1+I8) -> 5319.1361 | K8: =J8/J$14 -> 0.052809208 | L8: =(K8-F8)*100 -> 0.28092084 | M8: =(F8-K8)*100 -> -0.28092084 | N8: Small strategic allocation to faster-growing, higher-volatility economies.
A9: XBB | B9: iShares Core Canadian Universe Bond Index ETF | C9: Fixed income | D9: Canada, investment grade (CAD) | E9: CAD | F9: 0.25 | G9: 0.24626792 | H9: =Start_Value*G9 -> 24946.617 | I9: =Returns!F9 -> -0.012649253 | J9: =H9*(1+I9) -> 24631.061 | K9: =J9/J$14 -> 0.24454099 | L9: =(K9-F9)*100 -> -0.54590051 | M9: =(F9-K9)*100 -> 0.54590051 | N9: Core fixed income: government and investment-grade corporate bonds across maturities.
A10: XSB | B10: iShares Core Canadian Short Term Bond Index ETF | C10: Fixed income | D10: Canada, short maturities (CAD) | E10: CAD | F10: 0.1 | G10: 0.098894723 | H10: =Start_Value*G10 -> 10017.906 | I10: =Returns!F10 -> -0.0075570693 | J10: =H10*(1+I10) -> 9942.1998 | K10: =J10/J$14 -> 0.098707701 | L10: =(K10-F10)*100 -> -0.12922991 | M10: =(F10-K10)*100 -> 0.12922991 | N10: Lower interest-rate sensitivity and a liquidity reserve inside the bond sleeve.
A11: XHY | B11: iShares U.S. High Yield Bond Index ETF (CAD-Hedged) | C11: Fixed income | D11: US high-yield credit (CAD-hedged) | E11: CAD | F11: 0.05 | G11: 0.049675457 | H11: =Start_Value*G11 -> 5032.0587 | I11: =Returns!F11 -> -0.030673162 | J11: =H11*(1+I11) -> 4877.7096 | K11: =J11/J$14 -> 0.048426657 | L11: =(K11-F11)*100 -> -0.15733431 | M11: =(F11-K11)*100 -> 0.15733431 | N11: Small credit-risk income allocation; currency hedged so returns are not driven by USD/CAD.
B12: Equity sleeve | C12: Equity | F12: =SUMIF($C$5:$C$11,$C12,F$5:F$11) -> 0.6 | G12: =SUMIF($C$5:$C$11,$C12,G$5:G$11) -> 0.6051619 | H12: =SUMIF($C$5:$C$11,$C12,H$5:H$11) -> 61302.107 | I12: =J12/H12-1 -> -0.00048007231 | J12: =SUMIF($C$5:$C$11,$C12,J$5:J$11) -> 61272.678 | K12: =SUMIF($C$5:$C$11,$C12,K$5:K$11) -> 0.60832465 | L12: =(K12-F12)*100 -> 0.83246473
B13: Fixed-income sleeve | C13: Fixed income | F13: =SUMIF($C$5:$C$11,$C13,F$5:F$11) -> 0.4 | G13: =SUMIF($C$5:$C$11,$C13,G$5:G$11) -> 0.3948381 | H13: =SUMIF($C$5:$C$11,$C13,H$5:H$11) -> 39996.582 | I13: =J13/H13-1 -> -0.013641446 | J13: =SUMIF($C$5:$C$11,$C13,J$5:J$11) -> 39450.971 | K13: =SUMIF($C$5:$C$11,$C13,K$5:K$11) -> 0.39167535 | L13: =(K13-F13)*100 -> -0.83246473
B14: Hypothetical portfolio | F14: =SUM(F5:F11) -> 1 | G14: =SUM(G5:G11) -> 1 | H14: =SUM(H5:H11) -> 101298.69 | I14: =J14/H14-1 -> -0.0056766842 | J14: =SUM(J5:J11) -> 100723.65 | K14: =SUM(K5:K11) -> 1
B15: Check: target, start and end weights each sum to 100% | C15: =IF(AND(ABS(F14-1)<=Tol,ABS(G14-1)<=Tol,ABS(K14-1)<=Tol),"OK","CHECK") -> OK
A17: Benchmark
A18: VBAL | B18: Vanguard Balanced ETF Portfolio | C18: Balanced | D18: 60/40 global balanced fund of index ETFs (CAD) | E18: CAD | I18: =Returns!F12 -> -0.0050275755 | N18: A different issuer's 60/40 global balanced fund of index ETFs, priced in CAD. It shares the portfolio's 60/40 risk budget but not its holdings or regional weights, so the comparison shows the effect of allocation choices.
A20: Month-end maintain or rebalance test (illustrative)
B21: Largest sleeve drift (pp) | C21: =MAX(ABS(L12),ABS(L13)) -> 0.83246473
B22: Largest holding drift (pp) | C22: =MAX(ABS(MIN(L5:L11)),MAX(L5:L11)) -> 0.68869459
B23: Decision | C23: =IF(OR(C21>Class_Band,C22>Hold_Band),"Rebalance","Maintain") -> Maintain
B24: One-way turnover if reset to target | C24: =SUMPRODUCT(ABS(M5:M11))/2/100 -> 0.0096961543
B25: Illustrative reset cost at assumed bps (CAD) | C25: =J14*C24*Cost_bps/10000 -> 0

Sheet Returns
A1: Returns
A2: Independent educational research sample. Daily closes and ex-date distributions (blue) come from the saved snapshots; total-return indexes and returns are formulas.
A4: Series | B4: Start close | C4: End close | D4: Distributions in month | E4: Price return | F4: Total return | K4: Date | L4: XIC close | M4: XUU close | N4: XEF close | O4: XEC close | P4: XBB close | Q4: XSB close | R4: XHY close | S4: VBAL close | T4: XIC distribution | U4: XUU distribution | V4: XEF distribution | W4: XEC distribution | X4: XBB distribution | Y4: XSB distribution | Z4: XHY distribution | AA4: VBAL distribution | AB4: XIC total-return index | AC4: XUU total-return index | AD4: XEF total-return index | AE4: XEC total-return index | AF4: XBB total-return index | AG4: XSB total-return index | AH4: XHY total-return index | AI4: VBAL total-return index | AJ4: Portfolio cumulative return | AK4: Benchmark cumulative return | AL4: Active (portfolio - benchmark)
A5: XIC Canadian equity | B5: =L5 -> 58.02 | C5: =L26 -> 56.200001 | D5: =SUM(T5:T26) -> 0.285 | E5: =C5/B5-1 -> -0.031368488 | F5: =AB26/AB5-1 -> -0.026515966 | K5: 46265 | L5: 58.02 | M5: 78.099998 | N5: 52.369999 | O5: 44.169998 | P5: 27.6 | Q5: 26.73 | R5: 16.200001 | S5: 39.779999 | T5: 0 | U5: 0 | V5: 0 | W5: 0 | X5: 0 | Y5: 0 | Z5: 0 | AA5: 0 | AB5: 1 | AC5: 1 | AD5: 1 | AE5: 1 | AF5: 1 | AG5: 1 | AH5: 1 | AI5: 1 | AJ5: =Holdings!$G$5*AB5+Holdings!$G$6*AC5+Holdings!$G$7*AD5+Holdings!$G$8*AE5+Holdings!$G$9*AF5+Holdings!$G$10*AG5+Holdings!$G$11*AH5-1 -> 0 | AK5: =AI5-1 -> 0 | AL5: =AJ5-AK5 -> 0
A6: XUU US equity | B6: =M5 -> 78.099998 | C6: =M26 -> 79.440002 | D6: =SUM(U5:U26) -> 0.171 | E6: =C6/B6-1 -> 0.017157542 | F6: =AC26/AC5-1 -> 0.019346216 | K6: 46266 | L6: 57.310001 | M6: 78.150002 | N6: 52.09 | O6: 44.07 | P6: 27.59 | Q6: 26.719999 | R6: 16.17 | S6: 39.580002 | T6: 0 | U6: 0 | V6: 0 | W6: 0 | X6: 0 | Y6: 0 | Z6: 0 | AA6: 0 | AB6: =AB5*(L6+T6)/L5 -> 0.98776286 | AC6: =AC5*(M6+U6)/M5 -> 1.0006402 | AD6: =AD5*(N6+V6)/N5 -> 0.99465345 | AE6: =AE5*(O6+W6)/O5 -> 0.99773605 | AF6: =AF5*(P6+X6)/P5 -> 0.99963767 | AG6: =AG5*(Q6+Y6)/Q5 -> 0.99962588 | AH6: =AH5*(R6+Z6)/R5 -> 0.99814811 | AI6: =AI5*(S6+AA6)/S5 -> 0.99497242 | AJ6: =Holdings!$G$5*AB6+Holdings!$G$6*AC6+Holdings!$G$7*AD6+Holdings!$G$8*AE6+Holdings!$G$9*AF6+Holdings!$G$10*AG6+Holdings!$G$11*AH6-1 -> -0.0031970065 | AK6: =AI6-1 -> -0.0050275755 | AL6: =AJ6-AK6 -> 0.001830569
A7: XEF Intl developed equity | B7: =N5 -> 52.369999 | C7: =N26 -> 51.945 | D7: =SUM(V5:V26) -> 0 | E7: =C7/B7-1 -> -0.0081153188 | F7: =AD26/AD5-1 -> -0.0081153188 | K7: 46267 | L7: 57.740002 | M7: 77.699997 | N7: 52.049999 | O7: 44.119999 | P7: 27.52 | Q7: 26.66 | R7: 16.139999 | S7: 39.619999 | T7: 0 | U7: 0 | V7: 0 | W7: 0 | X7: 0 | Y7: 0 | Z7: 0 | AA7: 0 | AB7: =AB6*(L7+T7)/L6 -> 0.9951741 | AC7: =AC6*(M7+U7)/M6 -> 0.99487834 | AD7: =AD6*(N7+V7)/N6 -> 0.99388964 | AE7: =AE6*(O7+W7)/O6 -> 0.99886803 | AF7: =AF6*(P7+X7)/P6 -> 0.99710145 | AG7: =AG6*(Q7+Y7)/Q6 -> 0.99738123 | AH7: =AH6*(R7+Z7)/R6 -> 0.99629621 | AI7: =AI6*(S7+AA7)/S6 -> 0.99597788 | AJ7: =Holdings!$G$5*AB7+Holdings!$G$6*AC7+Holdings!$G$7*AD7+Holdings!$G$8*AE7+Holdings!$G$9*AF7+Holdings!$G$10*AG7+Holdings!$G$11*AH7-1 -> -0.004089344 | AK7: =AI7-1 -> -0.004022118 | AL7: =AJ7-AK7 -> -6.7226068e-05
A8: XEC Emerging markets equity | B8: =O5 -> 44.169998 | C8: =O26 -> 45.084999 | D8: =SUM(W5:W26) -> 0 | E8: =C8/B8-1 -> 0.020715439 | F8: =AE26/AE5-1 -> 0.020715439 | K8: 46268 | L8: 58.619999 | M8: 78.260002 | N8: 52.48 | O8: 44.16 | P8: 27.530001 | Q8: 26.67 | R8: 16.16 | S8: 39.849998 | T8: 0 | U8: 0 | V8: 0 | W8: 0 | X8: 0 | Y8: 0 | Z8: 0 | AA8: 0 | AB8: =AB7*(L8+T8)/L7 -> 1.0103412 | AC8: =AC7*(M8+U8)/M7 -> 1.0020487 | AD8: =AD7*(N8+V8)/N7 -> 1.0021005 | AE8: =AE7*(O8+W8)/O7 -> 0.99977364 | AF8: =AF7*(P8+X8)/P7 -> 0.99746378 | AG8: =AG7*(Q8+Y8)/Q7 -> 0.99775535 | AH8: =AH7*(R8+Z8)/R7 -> 0.99753081 | AI8: =AI7*(S8+AA8)/S7 -> 1.0017597 | AJ8: =Holdings!$G$5*AB8+Holdings!$G$6*AC8+Holdings!$G$7*AD8+Holdings!$G$8*AE8+Holdings!$G$9*AF8+Holdings!$G$10*AG8+Holdings!$G$11*AH8-1 -> 0.0018459474 | AK8: =AI8-1 -> 0.0017596706 | AL8: =AJ8-AK8 -> 8.6276778e-05
A9: XBB Canadian aggregate bonds | B9: =P5 -> 27.6 | C9: =P26 -> 27.17 | D9: =SUM(X5:X26) -> 0.081 | E9: =C9/B9-1 -> -0.015579721 | F9: =AF26/AF5-1 -> -0.012649253 | K9: 46269 | L9: 58.419998 | M9: 78.25 | N9: 52.650002 | O9: 45 | P9: 27.540001 | Q9: 26.68 | R9: 16.139999 | S9: 39.889999 | T9: 0 | U9: 0 | V9: 0 | W9: 0 | X9: 0 | Y9: 0 | Z9: 0 | AA9: 0 | AB9: =AB8*(L9+T9)/L8 -> 1.0068941 | AC9: =AC8*(M9+U9)/M8 -> 1.0019206 | AD9: =AD8*(N9+V9)/N8 -> 1.0053466 | AE9: =AE8*(O9+W9)/O8 -> 1.0187911 | AF9: =AF8*(P9+X9)/P8 -> 0.99782611 | AG9: =AG8*(Q9+Y9)/Q8 -> 0.99812947 | AH9: =AH8*(R9+Z9)/R8 -> 0.99629621 | AI9: =AI8*(S9+AA9)/S8 -> 1.0027652 | AJ9: =Holdings!$G$5*AB9+Holdings!$G$6*AC9+Holdings!$G$7*AD9+Holdings!$G$8*AE9+Holdings!$G$9*AF9+Holdings!$G$10*AG9+Holdings!$G$11*AH9-1 -> 0.0024792539 | AK9: =AI9-1 -> 0.0027652241 | AL9: =AJ9-AK9 -> -0.00028597022
A10: XSB Canadian short-term bonds | B10: =Q5 -> 26.73 | C10: =Q26 -> 26.459999 | D10: =SUM(Y5:Y26) -> 0.068 | E10: =C10/B10-1 -> -0.010101027 | F10: =AG26/AG5-1 -> -0.0075570693 | K10: 46273 | L10: 57.810001 | M10: 77.599998 | N10: 52.18 | O10: 44.900002 | P10: 27.52 | Q10: 26.66 | R10: 16.129999 | S10: 39.66 | T10: 0 | U10: 0 | V10: 0 | W10: 0 | X10: 0 | Y10: 0 | Z10: 0 | AA10: 0 | AB10: =AB9*(L10+T10)/L9 -> 0.99638057 | AC10: =AC9*(M10+U10)/M9 -> 0.99359795 | AD10: =AD9*(N10+V10)/N9 -> 0.99637199 | AE10: =AE9*(O10+W10)/O9 -> 1.0165271 | AF10: =AF9*(P10+X10)/P9 -> 0.99710145 | AG10: =AG9*(Q10+Y10)/Q9 -> 0.99738123 | AH10: =AH9*(R10+Z10)/R9 -> 0.99567891 | AI10: =AI9*(S10+AA10)/S9 -> 0.99698344 | AJ10: =Holdings!$G$5*AB10+Holdings!$G$6*AC10+Holdings!$G$7*AD10+Holdings!$G$8*AE10+Holdings!$G$9*AF10+Holdings!$G$10*AG10+Holdings!$G$11*AH10-1 -> -0.0030395052 | AK10: =AI10-1 -> -0.0030165645 | AL10: =AJ10-AK10 -> -2.2940685e-05
A11: XHY US high-yield bonds | B11: =R5 -> 16.200001 | C11: =R26 -> 15.62 | D11: =SUM(Z5:Z26) -> 0.084 | E11: =C11/B11-1 -> -0.035802522 | F11: =AH26/AH5-1 -> -0.030673162 | K11: 46274 | L11: 57.470001 | M11: 77.260002 | N11: 51.77 | O11: 44.82 | P11: 27.440001 | Q11: 26.629999 | R11: 16.110001 | S11: 39.494999 | T11: 0 | U11: 0 | V11: 0 | W11: 0 | X11: 0 | Y11: 0 | Z11: 0 | AA11: 0 | AB11: =AB10*(L11+T11)/L10 -> 0.99052052 | AC11: =AC10*(M11+U11)/M10 -> 0.9892446 | AD11: =AD10*(N11+V11)/N10 -> 0.98854309 | AE11: =AE10*(O11+W11)/O10 -> 1.0147159 | AF11: =AF10*(P11+X11)/P10 -> 0.9942029 | AG11: =AG10*(Q11+Y11)/Q10 -> 0.99625887 | AH11: =AH10*(R11+Z11)/R10 -> 0.99444444 | AI11: =AI10*(S11+AA11)/S10 -> 0.9928356 | AJ11: =Holdings!$G$5*AB11+Holdings!$G$6*AC11+Holdings!$G$7*AD11+Holdings!$G$8*AE11+Holdings!$G$9*AF11+Holdings!$G$10*AG11+Holdings!$G$11*AH11-1 -> -0.0070823197 | AK11: =AI11-1 -> -0.0071644006 | AL11: =AJ11-AK11 -> 8.2080888e-05
A12: VBAL benchmark | B12: =S5 -> 39.779999 | C12: =S26 -> 39.580002 | D12: =SUM(AA5:AA26) -> 0 | E12: =C12/B12-1 -> -0.0050275755 | F12: =AI26/AI5-1 -> -0.0050275755 | K12: 46275 | L12: 56.830002 | M12: 76.919998 | N12: 51.34 | O12: 43.990002 | P12: 27.280001 | Q12: 26.530001 | R12: 16.040001 | S12: 39.200001 | T12: 0 | U12: 0 | V12: 0 | W12: 0 | X12: 0 | Y12: 0 | Z12: 0 | AA12: 0 | AB12: =AB11*(L12+T12)/L11 -> 0.97948985 | AC12: =AC11*(M12+U12)/M11 -> 0.98489116 | AD12: =AD11*(N12+V12)/N11 -> 0.98033227 | AE12: =AE11*(O12+W12)/O11 -> 0.99592492 | AF12: =AF11*(P12+X12)/P11 -> 0.98840581 | AG12: =AG11*(Q12+Y12)/Q11 -> 0.99251781 | AH12: =AH11*(R12+Z12)/R11 -> 0.99012347 | AI12: =AI11*(S12+AA12)/S11 -> 0.98541986 | AJ12: =Holdings!$G$5*AB12+Holdings!$G$6*AC12+Holdings!$G$7*AD12+Holdings!$G$8*AE12+Holdings!$G$9*AF12+Holdings!$G$10*AG12+Holdings!$G$11*AH12-1 -> -0.014214897 | AK12: =AI12-1 -> -0.014580142 | AL12: =AJ12-AK12 -> 0.00036524437
A13: Hypothetical portfolio (sum of contributions) | F13: =Contributions!E14/100 -> -0.0056766842 | K13: 46276 | L13: 57.18 | M13: 77.709999 | N13: 51.98 | O13: 44.549999 | P13: 27.280001 | Q13: 26.52 | R13: 16.040001 | S13: 39.419998 | T13: 0 | U13: 0 | V13: 0 | W13: 0 | X13: 0 | Y13: 0 | Z13: 0 | AA13: 0 | AB13: =AB12*(L13+T13)/L12 -> 0.98552223 | AC13: =AC12*(M13+U13)/M12 -> 0.99500641 | AD13: =AD12*(N13+V13)/N12 -> 0.992553 | AE13: =AE12*(O13+W13)/O12 -> 1.0086031 | AF13: =AF12*(P13+X13)/P12 -> 0.98840581 | AG13: =AG12*(Q13+Y13)/Q12 -> 0.99214369 | AH13: =AH12*(R13+Z13)/R12 -> 0.99012347 | AI13: =AI12*(S13+AA13)/S12 -> 0.99095021 | AJ13: =Holdings!$G$5*AB13+Holdings!$G$6*AC13+Holdings!$G$7*AD13+Holdings!$G$8*AE13+Holdings!$G$9*AF13+Holdings!$G$10*AG13+Holdings!$G$11*AH13-1 -> -0.0086195638 | AK13: =AI13-1 -> -0.0090497894 | AL13: =AJ13-AK13 -> 0.00043022554
A14: Active return, portfolio minus benchmark (pp) | F14: =(F13-F12)*100 -> -0.064910867 | K14: 46279 | L14: 57.169998 | M14: 77.57 | N14: 52.259998 | O14: 43.599998 | P14: 27.25 | Q14: 26.52 | R14: 16.040001 | S14: 39.349998 | T14: 0 | U14: 0 | V14: 0 | W14: 0 | X14: 0 | Y14: 0 | Z14: 0 | AA14: 0 | AB14: =AB13*(L14+T14)/L13 -> 0.98534984 | AC14: =AC13*(M14+U14)/M13 -> 0.99321384 | AD14: =AD13*(N14+V14)/N13 -> 0.99789955 | AE14: =AE13*(O14+W14)/O13 -> 0.98709532 | AF14: =AF13*(P14+X14)/P13 -> 0.98731883 | AG14: =AG13*(Q14+Y14)/Q13 -> 0.99214369 | AH14: =AH13*(R14+Z14)/R13 -> 0.99012347 | AI14: =AI13*(S14+AA14)/S13 -> 0.98919054 | AJ14: =Holdings!$G$5*AB14+Holdings!$G$6*AC14+Holdings!$G$7*AD14+Holdings!$G$8*AE14+Holdings!$G$9*AF14+Holdings!$G$10*AG14+Holdings!$G$11*AH14-1 -> -0.0099450664 | AK14: =AI14-1 -> -0.01080946 | AL14: =AJ14-AK14 -> 0.00086439358
K15: 46280 | L15: 57.02 | M15: 77.330002 | N15: 51.619999 | O15: 43.43 | P15: 27.280001 | Q15: 26.530001 | R15: 15.98 | S15: 39.259998 | T15: 0 | U15: 0 | V15: 0 | W15: 0 | X15: 0 | Y15: 0 | Z15: 0 | AA15: 0 | AB15: =AB14*(L15+T15)/L14 -> 0.98276456 | AC15: =AC14*(M15+U15)/M14 -> 0.99014089 | AD15: =AD14*(N15+V15)/N14 -> 0.98567882 | AE15: =AE14*(O15+W15)/O14 -> 0.9832466 | AF15: =AF14*(P15+X15)/P14 -> 0.98840581 | AG15: =AG14*(Q15+Y15)/Q14 -> 0.99251781 | AH15: =AH14*(R15+Z15)/R14 -> 0.98641968 | AI15: =AI14*(S15+AA15)/S14 -> 0.98692809 | AJ15: =Holdings!$G$5*AB15+Holdings!$G$6*AC15+Holdings!$G$7*AD15+Holdings!$G$8*AE15+Holdings!$G$9*AF15+Holdings!$G$10*AG15+Holdings!$G$11*AH15-1 -> -0.012536438 | AK15: =AI15-1 -> -0.013071907 | AL15: =AJ15-AK15 -> 0.00053546937
A16: Chart-ready: the daily table at right (Date, Portfolio and Benchmark cumulative return) feeds the Overview line chart. Distributions are zero on the start date because they belong to the prior edition. | K16: 46281 | L16: 56.869999 | M16: 77.330002 | N16: 51.66 | O16: 43.619999 | P16: 27.299999 | Q16: 26.549999 | R16: 15.99 | S16: 39.27 | T16: 0 | U16: 0 | V16: 0 | W16: 0 | X16: 0 | Y16: 0 | Z16: 0 | AA16: 0 | AB16: =AB15*(L16+T16)/L15 -> 0.98017922 | AC16: =AC15*(M16+U16)/M15 -> 0.99014089 | AD16: =AD15*(N16+V16)/N15 -> 0.98644264 | AE16: =AE15*(O16+W16)/O15 -> 0.98754813 | AF16: =AF15*(P16+X16)/P15 -> 0.98913039 | AG16: =AG15*(Q16+Y16)/Q15 -> 0.99326598 | AH16: =AH15*(R16+Z16)/R15 -> 0.98703698 | AI16: =AI15*(S16+AA16)/S15 -> 0.98717953 | AJ16: =Holdings!$G$5*AB16+Holdings!$G$6*AC16+Holdings!$G$7*AD16+Holdings!$G$8*AE16+Holdings!$G$9*AF16+Holdings!$G$10*AG16+Holdings!$G$11*AH16-1 -> -0.012481959 | AK16: =AI16-1 -> -0.012820471 | AL16: =AJ16-AK16 -> 0.00033851192
K17: 46282 | L17: 57.459999 | M17: 78.209999 | N17: 52.099998 | O17: 44.439999 | P17: 27.48 | Q17: 26.620001 | R17: 16.059999 | S17: 39.615002 | T17: 0 | U17: 0 | V17: 0 | W17: 0 | X17: 0 | Y17: 0 | Z17: 0 | AA17: 0 | AB17: =AB16*(L17+T17)/L16 -> 0.99034813 | AC17: =AC16*(M17+U17)/M16 -> 1.0014085 | AD17: =AD16*(N17+V17)/N16 -> 0.99484437 | AE17: =AE16*(O17+W17)/O16 -> 1.0061128 | AF17: =AF16*(P17+X17)/P16 -> 0.99565214 | AG17: =AG16*(Q17+Y17)/Q16 -> 0.99588482 | AH17: =AH16*(R17+Z17)/R16 -> 0.99135795 | AI17: =AI16*(S17+AA17)/S16 -> 0.99585226 | AJ17: =Holdings!$G$5*AB17+Holdings!$G$6*AC17+Holdings!$G$7*AD17+Holdings!$G$8*AE17+Holdings!$G$9*AF17+Holdings!$G$10*AG17+Holdings!$G$11*AH17-1 -> -0.0037173121 | AK17: =AI17-1 -> -0.0041477402 | AL17: =AJ17-AK17 -> 0.00043042812
K18: 46283 | L18: 57.330002 | M18: 78.230003 | N18: 51.669998 | O18: 44.529999 | P18: 27.43 | Q18: 26.58 | R18: 16.030001 | S18: 39.549999 | T18: 0 | U18: 0 | V18: 0 | W18: 0 | X18: 0 | Y18: 0 | Z18: 0 | AA18: 0 | AB18: =AB17*(L18+T18)/L17 -> 0.98810757 | AC18: =AC17*(M18+U18)/M17 -> 1.0016646 | AD18: =AD17*(N18+V18)/N17 -> 0.98663355 | AE18: =AE17*(O18+W18)/O17 -> 1.0081503 | AF18: =AF17*(P18+X18)/P17 -> 0.99384058 | AG18: =AG17*(Q18+Y18)/Q17 -> 0.99438834 | AH18: =AH17*(R18+Z18)/R17 -> 0.98950617 | AI18: =AI17*(S18+AA18)/S17 -> 0.99421821 | AJ18: =Holdings!$G$5*AB18+Holdings!$G$6*AC18+Holdings!$G$7*AD18+Holdings!$G$8*AE18+Holdings!$G$9*AF18+Holdings!$G$10*AG18+Holdings!$G$11*AH18-1 -> -0.0055086703 | AK18: =AI18-1 -> -0.0057817886 | AL18: =AJ18-AK18 -> 0.00027311831
K19: 46286 | L19: 57.689999 | M19: 79.68 | N19: 52.369999 | O19: 45.740002 | P19: 27.49 | Q19: 26.620001 | R19: 16.049999 | S19: 39.950001 | T19: 0 | U19: 0 | V19: 0 | W19: 0 | X19: 0 | Y19: 0 | Z19: 0 | AA19: 0 | AB19: =AB18*(L19+T19)/L18 -> 0.99431227 | AC19: =AC18*(M19+U19)/M18 -> 1.0202305 | AD19: =AD18*(N19+V19)/N18 -> 1 | AE19: =AE18*(O19+W19)/O18 -> 1.0355446 | AF19: =AF18*(P19+X19)/P18 -> 0.99601447 | AG19: =AG18*(Q19+Y19)/Q18 -> 0.99588482 | AH19: =AH18*(R19+Z19)/R18 -> 0.99074065 | AI19: =AI18*(S19+AA19)/S18 -> 1.0042736 | AJ19: =Holdings!$G$5*AB19+Holdings!$G$6*AC19+Holdings!$G$7*AD19+Holdings!$G$8*AE19+Holdings!$G$9*AF19+Holdings!$G$10*AG19+Holdings!$G$11*AH19-1 -> 0.0038922134 | AK19: =AI19-1 -> 0.0042735543 | AL19: =AJ19-AK19 -> -0.00038134091
K20: 46287 | L20: 58.200001 | M20: 79.879997 | N20: 52.639999 | O20: 46.099998 | P20: 27.549999 | Q20: 26.639999 | R20: 16.07 | S20: 40.09 | T20: 0 | U20: 0 | V20: 0 | W20: 0 | X20: 0 | Y20: 0 | Z20: 0 | AA20: 0 | AB20: =AB19*(L20+T20)/L19 -> 1.0031024 | AC20: =AC19*(M20+U20)/M19 -> 1.0227913 | AD20: =AD19*(N20+V20)/N19 -> 1.0051556 | AE20: =AE19*(O20+W20)/O19 -> 1.0436948 | AF20: =AF19*(P20+X20)/P19 -> 0.99818836 | AG20: =AG19*(Q20+Y20)/Q19 -> 0.99663299 | AH20: =AH19*(R20+Z20)/R19 -> 0.99197524 | AI20: =AI19*(S20+AA20)/S19 -> 1.0077929 | AJ20: =Holdings!$G$5*AB20+Holdings!$G$6*AC20+Holdings!$G$7*AD20+Holdings!$G$8*AE20+Holdings!$G$9*AF20+Holdings!$G$10*AG20+Holdings!$G$11*AH20-1 -> 0.007926218 | AK20: =AI20-1 -> 0.0077928955 | AL20: =AJ20-AK20 -> 0.00013332253
K21: 46288 | L21: 57.290001 | M21: 79.43 | N21: 51.939999 | O21: 45.25 | P21: 27.35 | Q21: 26.52 | R21: 15.95 | S21: 39.720001 | T21: 0 | U21: 0 | V21: 0 | W21: 0 | X21: 0 | Y21: 0 | Z21: 0 | AA21: 0 | AB21: =AB20*(L21+T21)/L20 -> 0.98741814 | AC21: =AC20*(M21+U21)/M20 -> 1.0170295 | AD21: =AD20*(N21+V21)/N20 -> 0.99178919 | AE21: =AE20*(O21+W21)/O20 -> 1.024451 | AF21: =AF20*(P21+X21)/P20 -> 0.99094203 | AG21: =AG20*(Q21+Y21)/Q20 -> 0.99214369 | AH21: =AH20*(R21+Z21)/R20 -> 0.98456784 | AI21: =AI20*(S21+AA21)/S20 -> 0.99849177 | AJ21: =Holdings!$G$5*AB21+Holdings!$G$6*AC21+Holdings!$G$7*AD21+Holdings!$G$8*AE21+Holdings!$G$9*AF21+Holdings!$G$10*AG21+Holdings!$G$11*AH21-1 -> -0.0016274919 | AK21: =AI21-1 -> -0.0015082343 | AL21: =AJ21-AK21 -> -0.0001192576
K22: 46289 | L22: 56.889999 | M22: 79.470001 | N22: 51.93 | O22: 45.130001 | P22: 27.209999 | Q22: 26.459999 | R22: 15.79 | S22: 39.68 | T22: 0.285 | U22: 0.171 | V22: 0 | W22: 0 | X22: 0.081 | Y22: 0.068 | Z22: 0.084 | AA22: 0 | AB22: =AB21*(L22+T22)/L21 -> 0.98543604 | AC22: =AC21*(M22+U22)/M21 -> 1.0197311 | AD22: =AD21*(N22+V22)/N21 -> 0.99159827 | AE22: =AE21*(O22+W22)/O21 -> 1.0217343 | AF22: =AF21*(P22+X22)/P21 -> 0.9888043 | AG22: =AG21*(Q22+Y22)/Q21 -> 0.99244293 | AH22: =AH21*(R22+Z22)/R21 -> 0.97987649 | AI22: =AI21*(S22+AA22)/S21 -> 0.99748621 | AJ22: =Holdings!$G$5*AB22+Holdings!$G$6*AC22+Holdings!$G$7*AD22+Holdings!$G$8*AE22+Holdings!$G$9*AF22+Holdings!$G$10*AG22+Holdings!$G$11*AH22-1 -> -0.0022424913 | AK22: =AI22-1 -> -0.0025137878 | AL22: =AJ22-AK22 -> 0.00027129645
K23: 46290 | L23: 57.07 | M23: 79.845001 | N23: 52.439999 | O23: 45.560001 | P23: 27.32 | Q23: 26.530001 | R23: 15.8 | S23: 39.880001 | T23: 0 | U23: 0 | V23: 0 | W23: 0 | X23: 0 | Y23: 0 | Z23: 0 | AA23: 0 | AB23: =AB22*(L23+T23)/L22 -> 0.98855396 | AC23: =AC22*(M23+U23)/M22 -> 1.024543 | AD23: =AD22*(N23+V23)/N22 -> 1.0013366 | AE23: =AE22*(O23+W23)/O22 -> 1.0314694 | AF23: =AF22*(P23+X23)/P22 -> 0.99280169 | AG23: =AG22*(Q23+Y23)/Q22 -> 0.9950685 | AH23: =AH22*(R23+Z23)/R22 -> 0.98049708 | AI23: =AI22*(S23+AA23)/S22 -> 1.0025139 | AJ23: =Holdings!$G$5*AB23+Holdings!$G$6*AC23+Holdings!$G$7*AD23+Holdings!$G$8*AE23+Holdings!$G$9*AF23+Holdings!$G$10*AG23+Holdings!$G$11*AH23-1 -> 0.0023440106 | AK23: =AI23-1 -> 0.0025138837 | AL23: =AJ23-AK23 -> -0.00016987305
K24: 46293 | L24: 56.610001 | M24: 79.43 | N24: 52.27 | O24: 45.200001 | P24: 27.25 | Q24: 26.48 | R24: 15.72 | S24: 39.669998 | T24: 0 | U24: 0 | V24: 0 | W24: 0 | X24: 0 | Y24: 0 | Z24: 0 | AA24: 0 | AB24: =AB23*(L24+T24)/L23 -> 0.98058596 | AC24: =AC23*(M24+U24)/M23 -> 1.0192179 | AD24: =AD23*(N24+V24)/N23 -> 0.99809054 | AE24: =AE23*(O24+W24)/O23 -> 1.0233191 | AF24: =AF23*(P24+X24)/P23 -> 0.99025792 | AG24: =AG23*(Q24+Y24)/Q23 -> 0.99319309 | AH24: =AH23*(R24+Z24)/R23 -> 0.97553254 | AI24: =AI23*(S24+AA24)/S23 -> 0.99723478 | AJ24: =Holdings!$G$5*AB24+Holdings!$G$6*AC24+Holdings!$G$7*AD24+Holdings!$G$8*AE24+Holdings!$G$9*AF24+Holdings!$G$10*AG24+Holdings!$G$11*AH24-1 -> -0.0024129546 | AK24: =AI24-1 -> -0.0027652241 | AL24: =AJ24-AK24 -> 0.00035226951
K25: 46294 | L25: 56.57 | M25: 79.300003 | N25: 52.044998 | O25: 45.349998 | P25: 27.190001 | Q25: 26.459999 | R25: 15.67 | S25: 39.599998 | T25: 0 | U25: 0 | V25: 0 | W25: 0 | X25: 0 | Y25: 0 | Z25: 0 | AA25: 0 | AB25: =AB24*(L25+T25)/L24 -> 0.97989307 | AC25: =AC24*(M25+U25)/M24 -> 1.0175498 | AD25: =AD24*(N25+V25)/N24 -> 0.99379414 | AE25: =AE24*(O25+W25)/O24 -> 1.026715 | AF25: =AF24*(P25+X25)/P24 -> 0.98807756 | AG25: =AG24*(Q25+Y25)/Q24 -> 0.99244293 | AH25: =AH24*(R25+Z25)/R24 -> 0.97242969 | AI25: =AI24*(S25+AA25)/S24 -> 0.99547511 | AJ25: =Holdings!$G$5*AB25+Holdings!$G$6*AC25+Holdings!$G$7*AD25+Holdings!$G$8*AE25+Holdings!$G$9*AF25+Holdings!$G$10*AG25+Holdings!$G$11*AH25-1 -> -0.0039907213 | AK25: =AI25-1 -> -0.0045248947 | AL25: =AJ25-AK25 -> 0.00053417344
K26: 46295 | L26: 56.200001 | M26: 79.440002 | N26: 51.945 | O26: 45.084999 | P26: 27.17 | Q26: 26.459999 | R26: 15.62 | S26: 39.580002 | T26: 0 | U26: 0 | V26: 0 | W26: 0 | X26: 0 | Y26: 0 | Z26: 0 | AA26: 0 | AB26: =AB25*(L26+T26)/L25 -> 0.97348403 | AC26: =AC25*(M26+U26)/M25 -> 1.0193462 | AD26: =AD25*(N26+V26)/N25 -> 0.99188468 | AE26: =AE25*(O26+W26)/O25 -> 1.0207154 | AF26: =AF25*(P26+X26)/P25 -> 0.98735075 | AG26: =AG25*(Q26+Y26)/Q25 -> 0.99244293 | AH26: =AH25*(R26+Z26)/R25 -> 0.96932684 | AI26: =AI25*(S26+AA26)/S25 -> 0.99497242 | AJ26: =Holdings!$G$5*AB26+Holdings!$G$6*AC26+Holdings!$G$7*AD26+Holdings!$G$8*AE26+Holdings!$G$9*AF26+Holdings!$G$10*AG26+Holdings!$G$11*AH26-1 -> -0.0056766842 | AK26: =AI26-1 -> -0.0050275755 | AL26: =AJ26-AK26 -> -0.00064910867

Sheet Contributions
A1: Contribution to return
A2: Contribution = beginning weight x total return, in percentage points of portfolio return. Not formal performance attribution.
A4: Ticker | B4: Asset class | C4: Start weight | D4: Total return | E4: Contribution (pp) | F4: Share of portfolio return (signed) | G4: End weight | H4: Drift vs target
A5: XIC | B5: Equity | C5: =Holdings!G5 -> 0.20346772 | D5: =Holdings!I5 -> -0.026515966 | E5: =C5*D5*100 -> -0.5395143 | F5: =E5/E$14 -> 0.95040394 | G5: =Holdings!K5 -> 0.19920339 | H5: =Holdings!L5 -> -0.079661255
A6: XUU | B6: Equity | C6: =Holdings!G6 -> 0.25058089 | D6: =Holdings!I6 -> 0.019346216 | E6: =C6*D6*100 -> 0.48477919 | F6: =E6/E$14 -> -0.85398302 | G6: =Holdings!K6 -> 0.25688695 | H6: =Holdings!L6 -> 0.68869459
A7: XEF | B7: Equity | C7: =Holdings!G7 -> 0.099669551 | D7: =Holdings!I7 -> -0.0081153188 | E7: =C7*D7*100 -> -0.080885018 | F7: =E7/E$14 -> 0.14248638 | G7: =Holdings!K7 -> 0.099425106 | H7: =Holdings!L7 -> -0.057489447
A8: XEC | B8: Equity | C8: =Holdings!G8 -> 0.051443747 | D8: =Holdings!I8 -> 0.020715439 | E8: =C8*D8*100 -> 0.10656798 | F8: =E8/E$14 -> -0.18772928 | G8: =Holdings!K8 -> 0.052809208 | H8: =Holdings!L8 -> 0.28092084
A9: XBB | B9: Fixed income | C9: =Holdings!G9 -> 0.24626792 | D9: =Holdings!I9 -> -0.012649253 | E9: =C9*D9*100 -> -0.31151051 | F9: =E9/E$14 -> 0.54875434 | G9: =Holdings!K9 -> 0.24454099 | H9: =Holdings!L9 -> -0.54590051
A10: XSB | B10: Fixed income | C10: =Holdings!G10 -> 0.098894723 | D10: =Holdings!I10 -> -0.0075570693 | E10: =C10*D10*100 -> -0.074735427 | F10: =E10/E$14 -> 0.13165331 | G10: =Holdings!K10 -> 0.098707701 | H10: =Holdings!L10 -> -0.12922991
A11: XHY | B11: Fixed income | C11: =Holdings!G11 -> 0.049675457 | D11: =Holdings!I11 -> -0.030673162 | E11: =C11*D11*100 -> -0.15237034 | F11: =E11/E$14 -> 0.26841432 | G11: =Holdings!K11 -> 0.048426657 | H11: =Holdings!L11 -> -0.15733431
A12: Equity sleeve | B12: Equity | C12: =SUMIF($B$5:$B$11,$B12,C$5:C$11) -> 0.6051619 | D12: =E12/100/C12 -> -0.00048007231 | E12: =SUMIF($B$5:$B$11,$B12,E$5:E$11) -> -0.029052147 | F12: =E12/E$14 -> 0.051178023 | G12: =SUMIF($B$5:$B$11,$B12,G$5:G$11) -> 0.60832465 | H12: =(G12-Eq_Target)*100 -> 0.83246473
A13: Fixed-income sleeve | B13: Fixed income | C13: =SUMIF($B$5:$B$11,$B13,C$5:C$11) -> 0.3948381 | D13: =E13/100/C13 -> -0.013641446 | E13: =SUMIF($B$5:$B$11,$B13,E$5:E$11) -> -0.53861627 | F13: =E13/E$14 -> 0.94882198 | G13: =SUMIF($B$5:$B$11,$B13,G$5:G$11) -> 0.39167535 | H13: =(G13-FI_Target)*100 -> -0.83246473
A14: Hypothetical portfolio | C14: =SUM(C5:C11) -> 1 | D14: =E14/100 -> -0.0056766842 | E14: =SUM(E5:E11) -> -0.56766842 | F14: =SUM(F5:F11) -> 1 | G14: =SUM(G5:G11) -> 1
A17: Reconciliation
A18: Sum of contributions | B18: =E14/100 -> -0.0056766842
A19: Portfolio return from daily path | B19: =Returns!AJ26 -> -0.0056766842
A20: Absolute difference | B20: =ABS(B18-B19) -> 6.0715322e-17
A21: Tolerance | B21: =Tol -> 1e-09
A22: Status | B22: =IF(B20<=B21,"OK","CHECK") -> OK
A24: Allocation drift by sleeve
A25: Sleeve | B25: Target | C25: Start | D25: End | E25: Drift (pp) | F25: Band (pp) | G25: Within band
A26: Equity | B26: =Eq_Target -> 0.6 | C26: =C12 -> 0.6051619 | D26: =G12 -> 0.60832465 | E26: =(D26-B26)*100 -> 0.83246473 | F26: =Class_Band -> 2 | G26: =IF(ABS(E26)<=F26,"Yes","No") -> Yes
A27: Fixed income | B27: =FI_Target -> 0.4 | C27: =C13 -> 0.3948381 | D27: =G13 -> 0.39167535 | E27: =(D27-B27)*100 -> -0.83246473 | F27: =Class_Band -> 2 | G27: =IF(ABS(E27)<=F27,"Yes","No") -> Yes
A30: Chart-ready: contribution by holding (pp), in holdings order
A31: Ticker | B31: Asset class | C31: Contribution (pp)
A32: =A5 -> XIC | B32: =B5 -> Equity | C32: =E5 -> -0.5395143
A33: =A6 -> XUU | B33: =B6 -> Equity | C33: =E6 -> 0.48477919
A34: =A7 -> XEF | B34: =B7 -> Equity | C34: =E7 -> -0.080885018
A35: =A8 -> XEC | B35: =B8 -> Equity | C35: =E8 -> 0.10656798
A36: =A9 -> XBB | B36: =B9 -> Fixed income | C36: =E9 -> -0.31151051
A37: =A10 -> XSB | B37: =B10 -> Fixed income | C37: =E10 -> -0.074735427
A38: =A11 -> XHY | B38: =B11 -> Fixed income | C38: =E11 -> -0.15237034

Sheet Assumptions
A1: Assumptions and inputs
A2: Independent educational research sample. Hypothetical portfolio. Blue cells are inputs; every other number in the workbook is calculated from them.
A4: Parameter | B4: Value | C4: Unit | D4: Note
A5: Edition | B5: September 2026 | D5: Monthly edition; information cut off at the close of the as-of date.
A6: Start date (prior month-end close) | B6: 46265 | C6: date | D6: Beginning prices and weights.
A7: As-of date (cutoff close) | B7: 46295 | C7: date | D7: Last observation used. Nothing after this date is used.
A8: Currency | B8: CAD | D8: All ETF proxies are CAD-listed, so returns are already in CAD.
A9: Starting portfolio value | B9: 101298.69 | C9: CAD | D9: Hypothetical. First edition starts at C$100,000; later editions carry the prior ending value.
A10: Equity target weight | B10: 0.6 | C10: weight | D10: Strategic target.
A11: Fixed-income target weight | B11: =1-B10 -> 0.4 | C11: weight | D11: Equals 1 minus the equity target.
A12: Asset-class drift band | B12: 2 | C12: pp | D12: Rebalance if any sleeve is further than this from target at month-end.
A13: Holding drift band | B13: 1.5 | C13: pp | D13: Rebalance if any holding is further than this from target at month-end.
A14: Transaction cost | B14: 0 | C14: bps | D14: One-way cost applied to an illustrative reset. Zero: month returns exclude trading costs.
A15: Reconciliation tolerance | B15: 1e-09 | C15: fraction | D15: Maximum allowed gap between summed contributions and the daily portfolio path.
A17: Method notes
A18: Return definition | B18: Total return from daily closes with distributions reinvested at the ex-date close. Price return (no distributions) is shown beside it. No withholding or income tax.
A19: Fees and costs | B19: ETF prices are net of each fund's management expenses. Trading costs and taxes are excluded; the transaction-cost input above only prices an illustrative reset.
A20: Currency | B20: XUU, XEF and XEC are CAD-listed and unhedged, so foreign-currency moves are already in their CAD returns; XHY is CAD-hedged. Bank of Canada USD/CAD is a daily average rate and is used only for commentary.
A21: ETF proxies | B21: Seven liquid iShares ETFs stand in for asset-class exposures. The benchmark is a different issuer's 60/40 balanced fund, VBAL, which also reports net of fees.
A22: Weights and contributions | B22: Contribution = beginning weight x total return, in percentage points of portfolio return. It is a contribution table, not formal performance attribution.
A23: Rebalancing convention | B23: Threshold review at each month-end close. If any asset-class weight is more than 2.0 pp from target, or any holding more than 1.5 pp from target, the portfolio is assumed rebalanced to target at that close. Otherwise the drifted weights carry into the next month. The first edition starts at target on the inception date.
A24: Data quality | B24: No missing or stale observation is filled. USD/CAD (daily average): end value is the Sep 29 observation (no publication on Sep 30). Canada 2-year yield: end value is the Sep 29 observation (no publication on Sep 30). Canada 10-year yield: end value is the Sep 29 observation (no publication on Sep 30).
A25: Carry-forward | B25: prior month-end drifted weights, as the prior decision was Maintain.

Sheet Sources
A1: Sources and snapshots
A2: Every input comes from a saved public snapshot (data/snapshots). Observation or publication date and retrieval date are shown. Facts are cited by [ref] in the report.
A4: Ref | B4: Kind | C4: Publisher | D4: Title / series | E4: URL requested | F4: Observation or publication | G4: Retrieved | H4: Snapshot file | I4: SHA-256 (first 12)
A5: 3 | B5: Document | C5: Bank of Canada | D5: rate announcement | E5: https://www.bankofcanada.ca/2026/09/fad-press-release-2026-09-02/ | F5: Sep 2, 2026 | G5: 2026-10-14 | H5: data/snapshots/2026-09/docs/boc_2026_09_02.txt | I5: 4ab4ce0b7753
A6: 4 | B6: Document | C6: Federal Reserve Board | D6: FOMC statement | E6: https://www.federalreserve.gov/newsevents/pressreleases/monetary20260916a.htm | F6: Sep 16, 2026 | G6: 2026-10-14 | H6: data/snapshots/2026-09/docs/fed_2026_09_16.txt | I6: 3c5c918b7daf
A7: 5 | B7: Document | C7: Federal Reserve | D7: FOMC meeting calendar | E7: https://www.federalreserve.gov/monetarypolicy/fomccalendars.htm | F7: schedule | G7: 2026-10-14 | H7: data/snapshots/2026-09/docs/fomc_calendar.txt | I7: 691e7e5f64d9
A8: 1 | B8: Prices | C8: Yahoo Finance (chart API) | D8: XIC.TO: daily close and ex-dividend events | E8: https://query1.finance.yahoo.com/v8/finance/chart/XIC.TO?period1=1787097600&period2=1790812800&interval=1d&events=div%7Csplit | F8: 2026-08-31 to 2026-09-30 | G8: 2026-10-14 | H8: data/snapshots/2026-09/prices/XIC.TO.json | I8: d69e8a214db9
A9: 1 | B9: Prices | C9: Yahoo Finance (chart API) | D9: XUU.TO: daily close and ex-dividend events | E9: https://query1.finance.yahoo.com/v8/finance/chart/XUU.TO?period1=1787097600&period2=1790812800&interval=1d&events=div%7Csplit | F9: 2026-08-31 to 2026-09-30 | G9: 2026-10-14 | H9: data/snapshots/2026-09/prices/XUU.TO.json | I9: e390ecb59d59
A10: 1 | B10: Prices | C10: Yahoo Finance (chart API) | D10: XEF.TO: daily close and ex-dividend events | E10: https://query1.finance.yahoo.com/v8/finance/chart/XEF.TO?period1=1787097600&period2=1790812800&interval=1d&events=div%7Csplit | F10: 2026-08-31 to 2026-09-30 | G10: 2026-10-14 | H10: data/snapshots/2026-09/prices/XEF.TO.json | I10: 16a85060ba54
A11: 1 | B11: Prices | C11: Yahoo Finance (chart API) | D11: XEC.TO: daily close and ex-dividend events | E11: https://query1.finance.yahoo.com/v8/finance/chart/XEC.TO?period1=1787097600&period2=1790812800&interval=1d&events=div%7Csplit | F11: 2026-08-31 to 2026-09-30 | G11: 2026-10-14 | H11: data/snapshots/2026-09/prices/XEC.TO.json | I11: d711eb8ef521
A12: 1 | B12: Prices | C12: Yahoo Finance (chart API) | D12: XBB.TO: daily close and ex-dividend events | E12: https://query1.finance.yahoo.com/v8/finance/chart/XBB.TO?period1=1787097600&period2=1790812800&interval=1d&events=div%7Csplit | F12: 2026-08-31 to 2026-09-30 | G12: 2026-10-14 | H12: data/snapshots/2026-09/prices/XBB.TO.json | I12: 3d250b191d28
A13: 1 | B13: Prices | C13: Yahoo Finance (chart API) | D13: XSB.TO: daily close and ex-dividend events | E13: https://query1.finance.yahoo.com/v8/finance/chart/XSB.TO?period1=1787097600&period2=1790812800&interval=1d&events=div%7Csplit | F13: 2026-08-31 to 2026-09-30 | G13: 2026-10-14 | H13: data/snapshots/2026-09/prices/XSB.TO.json | I13: e9fd99087d2c
A14: 1 | B14: Prices | C14: Yahoo Finance (chart API) | D14: XHY.TO: daily close and ex-dividend events | E14: https://query1.finance.yahoo.com/v8/finance/chart/XHY.TO?period1=1787097600&period2=1790812800&interval=1d&events=div%7Csplit | F14: 2026-08-31 to 2026-09-30 | G14: 2026-10-14 | H14: data/snapshots/2026-09/prices/XHY.TO.json | I14: 03d5d4afe1f2
A15: 1 | B15: Prices | C15: Yahoo Finance (chart API) | D15: VBAL.TO: daily close and ex-dividend events | E15: https://query1.finance.yahoo.com/v8/finance/chart/VBAL.TO?period1=1787097600&period2=1790812800&interval=1d&events=div%7Csplit | F15: 2026-08-31 to 2026-09-30 | G15: 2026-10-14 | H15: data/snapshots/2026-09/prices/VBAL.TO.json | I15: 74e129e8b636
A16: 2 | B16: Macro | C16: Bank of Canada Valet API | D16: Series FXUSDCAD | E16: https://www.bankofcanada.ca/valet/observations/FXUSDCAD/json?start_date=2026-08-21&end_date=2026-09-30 | F16: to 2026-09-30 | G16: 2026-10-14 | H16: data/snapshots/2026-09/macro/FXUSDCAD.json | I16: f20df89bfe51
... A27: 6 | B27: Document | C27: Issuer fund page | D27: vanguard_vbal | E27: https://www.vanguard.ca/en/product/etf/asset-allocation/9578/vanguard-balanced-etf-portfolio | F27: Undated; objective text | G27: 2026-10-14 | H27: data/snapshots/2026-09/docs/vanguard_vbal.txt | I27: 44a1f87db53c
A29: Data-quality flags
A30: USD/CAD (daily average): end value is the Sep 29 observation (no publication on Sep 30).
A31: Canada 2-year yield: end value is the Sep 29 observation (no publication on Sep 30).
A32: Canada 10-year yield: end value is the Sep 29 observation (no publication on Sep 30).
A34: Documents [3] and [4] were published before the cutoff. Fund pages and the FOMC calendar were retrieved after the cutoff and are used only for stable descriptions and a schedule fixed in advance.
